emtl/__init__.py
emtl/basics.py
emtl/data.py
emtl/data_cache.py
emtl/utils.py
emtl/custom_data_getters/__init__.py
emtl/custom_data_getters/wpuq.py
emt_loader-0.0.6.dist-info/METADATA
emt_loader-0.0.6.dist-info/WHEEL
emt_loader-0.0.6.dist-info/licenses/LICENSE
emt_loader-0.0.6.dist-info/RECORD
