Metadata-Version: 2.4
Name: emt-loader
Version: 0.0.6
Summary: EMT Data Loader
Project-URL: Homepage, https://www.epe.ed.tum.de/en/emt/homepage/
Author-email: Linus Sander <linus.sander@tum.de>, Lennart Morlock <lennart.morlock@tum.de>, Manuel Katholnigg <manuel.katholnigg@tum.de>, Christoph Goebel <christoph.goebel@tum.de>
License-Expression: Apache-2.0
License-File: LICENSE
Classifier: Operating System :: OS Independent
Classifier: Programming Language :: Python :: 3
Requires-Python: >=3.10
Requires-Dist: pandas>=2
Requires-Dist: tqdm>=4
Requires-Dist: yaspin>=3
